MANIFEST.in
README.md
README.zh-CN.md
requirements.txt
setup.py
keras_transformer/__init__.py
keras_transformer/backend.py
keras_transformer/gelu.py
keras_transformer/transformer.py
keras_transformer.egg-info/PKG-INFO
keras_transformer.egg-info/SOURCES.txt
keras_transformer.egg-info/dependency_links.txt
keras_transformer.egg-info/requires.txt
keras_transformer.egg-info/top_level.txt
tests/__init__.py
tests/test_decode.py
tests/test_gelu.py
tests/test_get_decoders.py
tests/test_get_encoders.py
tests/test_get_model.py
tests/test_suffix_repeat.py
tests/test_translate.py